ws/webpasswd/__init__.py
ws/webpasswd/update.py
ws/webpasswd/web.py
ws/webpasswd/templates/form.html
ws/webpasswd/tests/__init__.py
ws/webpasswd/tests/test_update.py
ws/webpasswd/tests/test_web.py
ws.webpasswd-2.2.0.dist-info/METADATA
ws.webpasswd-2.2.0.dist-info/WHEEL
ws.webpasswd-2.2.0.dist-info/entry_points.txt
ws.webpasswd-2.2.0.dist-info/RECORD
