Metadata-Version: 2.3
Name: ws.webpasswd
Version: 2.2.0
Summary: Change a UNIX password via web UI
Project-URL: Repository, https://github.com/wosc/webpasswd
Author-email: Wolfgang Schnerring <wosc@wosc.de>
License:  BSD-3-Clause
Requires-Python: >=3.7
Requires-Dist: flask
Requires-Dist: flask-wtf
Requires-Dist: python-pam>=2.0.0
Requires-Dist: six
Requires-Dist: wtforms
Provides-Extra: test
Requires-Dist: pytest; extra == 'test'
Requires-Dist: pytest-cov; extra == 'test'
